tork_governance/__init__.py
tork_governance/core.py
tork_governance/adapters/__init__.py
tork_governance/adapters/agentgpt.py
tork_governance/adapters/anthropic_sdk.py
tork_governance/adapters/arize.py
tork_governance/adapters/autogen.py
tork_governance/adapters/aws_bedrock.py
tork_governance/adapters/azure_openai.py
tork_governance/adapters/babyagi.py
tork_governance/adapters/chromadb.py
tork_governance/adapters/cohere_sdk.py
tork_governance/adapters/crewai.py
tork_governance/adapters/dify.py
tork_governance/adapters/django.py
tork_governance/adapters/dspy.py
tork_governance/adapters/fastapi.py
tork_governance/adapters/flask.py
tork_governance/adapters/flowise.py
tork_governance/adapters/google_gemini.py
tork_governance/adapters/guardrails_ai.py
tork_governance/adapters/guidance.py
tork_governance/adapters/haystack.py
tork_governance/adapters/helicone.py
tork_governance/adapters/huggingface.py
tork_governance/adapters/humanloop.py
tork_governance/adapters/instructor.py
tork_governance/adapters/langchain.py
tork_governance/adapters/langflow.py
tork_governance/adapters/langfuse.py
tork_governance/adapters/langsmith.py
tork_governance/adapters/litellm.py
tork_governance/adapters/llamaindex.py
tork_governance/adapters/lmql.py
tork_governance/adapters/marvin.py
tork_governance/adapters/mcp.py
tork_governance/adapters/metagpt.py
tork_governance/adapters/milvus.py
tork_governance/adapters/nemo_guardrails.py
tork_governance/adapters/ollama.py
tork_governance/adapters/openai_agents.py
tork_governance/adapters/openai_sdk.py
tork_governance/adapters/outlines.py
tork_governance/adapters/phoenix.py
tork_governance/adapters/pinecone.py
tork_governance/adapters/portkey.py
tork_governance/adapters/promptlayer.py
tork_governance/adapters/pydantic_ai.py
tork_governance/adapters/qdrant.py
tork_governance/adapters/semantic_kernel.py
tork_governance/adapters/starlette.py
tork_governance/adapters/superagi.py
tork_governance/adapters/vllm.py
tork_governance/adapters/wandb.py
tork_governance-0.16.0.dist-info/METADATA
tork_governance-0.16.0.dist-info/WHEEL
tork_governance-0.16.0.dist-info/top_level.txt
tork_governance-0.16.0.dist-info/RECORD
