Metadata-Version: 2.4
Name: tork-governance
Version: 0.16.0
Summary: On-device AI governance with PII detection and cryptographic receipts
Author-email: Tork Network <developers@tork.network>
License: MIT
Project-URL: Homepage, https://tork.network
Project-URL: Documentation, https://docs.tork.network
Project-URL: Repository, https://github.com/torknetwork/tork-governance-python
Project-URL: Changelog, https://github.com/torknetwork/tork-governance-python/blob/main/CHANGELOG.md
Keywords: ai,governance,pii,privacy,security,llm,langchain,crewai
Classifier: Development Status :: 4 - Beta
Classifier: Intended Audience :: Developers
Classifier: License :: OSI Approved :: MIT License
Classifier: Operating System :: OS Independent
Classifier: Programming Language :: Python :: 3
Classifier: Programming Language :: Python :: 3.9
Classifier: Programming Language :: Python :: 3.10
Classifier: Programming Language :: Python :: 3.11
Classifier: Programming Language :: Python :: 3.12
Classifier: Topic :: Security
Classifier: Topic :: Software Development :: Libraries :: Python Modules
Requires-Python: >=3.9
Provides-Extra: langchain
Requires-Dist: langchain>=0.1.0; extra == "langchain"
Provides-Extra: crewai
Requires-Dist: crewai>=0.1.0; extra == "crewai"
Provides-Extra: autogen
Requires-Dist: pyautogen>=0.2.0; extra == "autogen"
Provides-Extra: openai
Requires-Dist: openai>=1.0.0; extra == "openai"
Provides-Extra: fastapi
Requires-Dist: fastapi>=0.100.0; extra == "fastapi"
Requires-Dist: starlette>=0.27.0; extra == "fastapi"
Provides-Extra: django
Requires-Dist: django>=4.0; extra == "django"
Provides-Extra: flask
Requires-Dist: flask>=2.0; extra == "flask"
Provides-Extra: huggingface
Requires-Dist: transformers>=4.30.0; extra == "huggingface"
Requires-Dist: torch>=2.0.0; extra == "huggingface"
Provides-Extra: all
Requires-Dist: langchain>=0.1.0; extra == "all"
Requires-Dist: crewai>=0.1.0; extra == "all"
Requires-Dist: pyautogen>=0.2.0; extra == "all"
Requires-Dist: openai>=1.0.0; extra == "all"
Requires-Dist: fastapi>=0.100.0; extra == "all"
Requires-Dist: starlette>=0.27.0; extra == "all"
Requires-Dist: django>=4.0; extra == "all"
Requires-Dist: flask>=2.0; extra == "all"
Provides-Extra: dev
Requires-Dist: pytest>=7.0; extra == "dev"
Requires-Dist: pytest-cov>=4.0; extra == "dev"
Requires-Dist: pytest-asyncio>=0.21.0; extra == "dev"
Requires-Dist: black>=23.0; extra == "dev"
Requires-Dist: mypy>=1.0; extra == "dev"
Requires-Dist: ruff>=0.1.0; extra == "dev"
